setup.cfg
setup.py
lunaticlog.egg-info/PKG-INFO
lunaticlog.egg-info/SOURCES.txt
lunaticlog.egg-info/dependency_links.txt
lunaticlog.egg-info/top_level.txt
src/__init__.py
src/log_generator.py
tests/__init__.py
tests/log_generator_test.py