Metadata-Version: 1.0
Name: lunaticlog
Version: 0.0.dev8
Summary: A log generator to test your monitor system.
Home-page: https://github.com/xuwenyihust/lunaticlog
Author: Wenyi Xu
Author-email: wenyixu101@gmail.com
License: MIT
Keywords: log monitor apache
Platform: UNKNOWN
